README.rst
setup.py
examples/DQN.py
examples/__init__.py
examples/chainer_test_DDPG.py
examples/chainer_test_DQN.py
examples/chainer_test_DQN_TB.py
examples/chainer_test_PCL.py
examples/chainer_test_PPO.py
examples/marlo_threading_examples.py
examples/multi_agent.py
examples/multiagent_chainer_test_DQN.py
examples/multiagentexample.py
examples/multiagentexamplechainer.py
examples/single_agent.py
examples/submission_random_agent.py
examples/test.py
examples/test_random_3game_mission.py
examples/test_thread_exception.py
marlo/__init__.py
marlo/base_env_builder.py
marlo/commands.py
marlo/constants.py
marlo/crowdai_helpers.py
marlo/launch_minecraft_in_background.py
marlo/utils.py
marlo.egg-info/PKG-INFO
marlo.egg-info/SOURCES.txt
marlo.egg-info/dependency_links.txt
marlo.egg-info/not-zip-safe
marlo.egg-info/pbr.json
marlo.egg-info/requires.txt
marlo.egg-info/top_level.txt
marlo/envs/__init__.py
marlo/envs/make_env.py
marlo/envs/Attic/__init__.py
marlo/envs/Attic/main.py
marlo/envs/Attic/templates/mission.xml
marlo/envs/BuildbattleTrain1/__init__.py
marlo/envs/BuildbattleTrain1/main.py
marlo/envs/BuildbattleTrain1/templates/mission.xml
marlo/envs/BuildbattleTrain2/__init__.py
marlo/envs/BuildbattleTrain2/main.py
marlo/envs/BuildbattleTrain2/templates/mission.xml
marlo/envs/BuildbattleTrain3/__init__.py
marlo/envs/BuildbattleTrain3/main.py
marlo/envs/BuildbattleTrain3/templates/mission.xml
marlo/envs/BuildbattleTrain4/__init__.py
marlo/envs/BuildbattleTrain4/main.py
marlo/envs/BuildbattleTrain4/templates/mission.xml
marlo/envs/BuildbattleTrain5/__init__.py
marlo/envs/BuildbattleTrain5/main.py
marlo/envs/BuildbattleTrain5/templates/mission.xml
marlo/envs/CatchTheMob/__init__.py
marlo/envs/CatchTheMob/main.py
marlo/envs/CatchTheMob/templates/mission.xml
marlo/envs/CliffWalking/__init__.py
marlo/envs/CliffWalking/main.py
marlo/envs/CliffWalking/templates/mission.xml
marlo/envs/DefaultFlatWorld/__init__.py
marlo/envs/DefaultFlatWorld/main.py
marlo/envs/DefaultFlatWorld/templates/mission.xml
marlo/envs/DefaultWorld/__init__.py
marlo/envs/DefaultWorld/main.py
marlo/envs/DefaultWorld/templates/mission.xml
marlo/envs/Eating/__init__.py
marlo/envs/Eating/main.py
