Metadata-Version: 1.0
Name: marlo
Version: 0.0.1.dev22
Summary: Marlo
Home-page: https://github.com/crowdAI/marlo
Author: S.P. Mohanty
Author-email: sharada.mohanty@epfl.ch
License: MIT License
Platform: UNKNOWN
